keynet_core/__init__.py
keynet_core/py.typed
keynet_core/cli/__init__.py
keynet_core/cli/main.py
keynet_core/cli/commands/__init__.py
keynet_core/cli/commands/login.py
keynet_core/cli/commands/logout.py
keynet_core/clients/__init__.py
keynet_core/clients/backend.py
keynet_core/clients/docker.py
keynet_core/config/__init__.py
keynet_core/config/manager.py
keynet_core/parsing/__init__.py
keynet_core/parsing/decorator.py
keynet_core/security/__init__.py
keynet_core/security/autoload.py
keynet_core/security/patterns.py
keynet_core/security/redaction.py
keynet_core/validation/__init__.py
keynet_core/validation/syntax.py
keynet_autoload.pth
keynet_core-0.8.5.dist-info/METADATA
keynet_core-0.8.5.dist-info/WHEEL
keynet_core-0.8.5.dist-info/entry_points.txt
keynet_core-0.8.5.dist-info/RECORD
