Metadata-Version: 2.4
Name: keynet-core
Version: 0.8.5
Summary: Core utilities and models for keynet packages
Project-URL: Homepage, https://github.com/WIM-Corporation/keynet
Project-URL: Bug Tracker, https://github.com/WIM-Corporation/keynet/issues
Author-email: hbjs <hbjs97@naver.com>
License: MIT
Keywords: core,keynet,utilities
Classifier: Development Status :: 3 - Alpha
Classifier: Intended Audience :: Developers
Classifier: License :: OSI Approved :: MIT License
Classifier: Programming Language :: Python :: 3
Classifier: Programming Language :: Python :: 3.9
Classifier: Programming Language :: Python :: 3.10
Classifier: Programming Language :: Python :: 3.11
Classifier: Programming Language :: Python :: 3.12
Requires-Python: >=3.9
Requires-Dist: boto3>=1.39.2
Requires-Dist: deprecated>=1.2.18
Requires-Dist: docker>=7.0.0
Requires-Dist: httpx>=0.27.0
Requires-Dist: mlflow==3.1.1
Requires-Dist: rich>=13.0.0
Requires-Dist: types-deprecated>=1.2.15.20250304
